LICENSE
catconfig.py
catconfig-0.1.1.dist-info/LICENSE
catconfig-0.1.1.dist-info/WHEEL
catconfig-0.1.1.dist-info/METADATA
catconfig-0.1.1.dist-info/RECORD
