Metadata-Version: 2.1
Name: catconfig
Version: 0.1.1
Summary: 🐱Make more easy for reading/validating/updating config for python app
Home-page: https://github.com/dev-techmoe/python-catconfig
License: MIT
Keywords: config,catconfig,configure,setting
Author: dev-techmoe
Author-email: me@lolicookie.com
Requires-Python: >=3.5,<4.0
Classifier: License :: OSI Approved :: MIT License
Classifier: Programming Language :: Python :: 3
Classifier: Programming Language :: Python :: 3.5
Classifier: Programming Language :: Python :: 3.6
Classifier: Programming Language :: Python :: 3.7
Classifier: Programming Language :: Python :: 3.8
Classifier: Topic :: Software Development
Classifier: Topic :: Software Development :: Libraries
Project-URL: Repository, https://github.com/dev-techmoe/python-catconfig
